geraldo3/__init__.py
geraldo3/barcodes.py
geraldo3/base.py
geraldo3/cache.py
geraldo3/charts.py
geraldo3/crossreference.py
geraldo3/exceptions.py
geraldo3/generators/__init__.py
geraldo3/generators/base.py
geraldo3/generators/csvgen.py
geraldo3/generators/html.py
geraldo3/generators/pdf.py
geraldo3/generators/text.py
geraldo3/generators/xmlstruct.py
geraldo3/graphics.py
geraldo3/models.py
geraldo3/utils.py
geraldo3/version.py
geraldo3/widgets.py
geraldo3-0.2.0.dist-info/METADATA
geraldo3-0.2.0.dist-info/WHEEL
geraldo3-0.2.0.dist-info/RECORD
